fastlane_bot/__init__.py
fastlane_bot/bot.py
fastlane_bot/config/__init__.py
fastlane_bot/config/base.py
fastlane_bot/config/cloaker.py
fastlane_bot/config/config.py
fastlane_bot/config/connect.py
fastlane_bot/config/constants.py
fastlane_bot/config/db.py
fastlane_bot/config/logger.py
fastlane_bot/config/multicaller.py
fastlane_bot/config/network.py
fastlane_bot/config/provider.py
fastlane_bot/config/selectors.py
fastlane_bot/data/__init__.py
fastlane_bot/data/abi.py
fastlane_bot/data/bancor_v2_pairs.csv
fastlane_bot/data/blockchain_data/arbitrum_one/static_pool_data.csv
fastlane_bot/data/blockchain_data/arbitrum_one/tokens.csv
fastlane_bot/data/blockchain_data/arbitrum_one/uniswap_v2_event_mappings.csv
fastlane_bot/data/blockchain_data/arbitrum_one/uniswap_v3_event_mappings.csv
fastlane_bot/data/blockchain_data/coinbase_base/solidly_v2_event_mappings.csv
fastlane_bot/data/blockchain_data/coinbase_base/static_pool_data.csv
fastlane_bot/data/blockchain_data/coinbase_base/tokens.csv
fastlane_bot/data/blockchain_data/coinbase_base/uniswap_v2_event_mappings.csv
fastlane_bot/data/blockchain_data/coinbase_base/uniswap_v3_event_mappings.csv
fastlane_bot/data/blockchain_data/ethereum/solidly_v2_event_mappings.csv
fastlane_bot/data/blockchain_data/ethereum/static_pool_data.csv
fastlane_bot/data/blockchain_data/ethereum/tokens.csv
fastlane_bot/data/blockchain_data/ethereum/uniswap_v2_event_mappings.csv
fastlane_bot/data/blockchain_data/ethereum/uniswap_v3_event_mappings.csv
fastlane_bot/data/blockchain_data/fantom/solidly_v2_event_mappings.csv
fastlane_bot/data/blockchain_data/fantom/static_pool_data.csv
fastlane_bot/data/blockchain_data/fantom/tokens.csv
fastlane_bot/data/blockchain_data/fantom/uniswap_v2_event_mappings.csv
fastlane_bot/data/blockchain_data/fantom/uniswap_v3_event_mappings.csv
fastlane_bot/data/blockchain_data/linea/solidly_v2_event_mappings.csv
fastlane_bot/data/blockchain_data/linea/static_pool_data.csv
fastlane_bot/data/blockchain_data/linea/tokens.csv
fastlane_bot-3.2.7.dist-info/LICENSE
fastlane_bot-3.2.7.dist-info/METADATA
fastlane_bot-3.2.7.dist-info/WHEEL
fastlane_bot-3.2.7.dist-info/RECORD
