Metadata-Version: 2.1
Name: fastlane-bot
Version: 3.2.7
Summary: Carbon Arbitrage Bot, an open-source arbitrage protocol, allows any user to perform arbitrage between Bancor ecosystem protocols and external exchanges and redirect arbitrage profits back to the protocol.
License: MIT
Author: Bancor Network
Author-email: services@bancor.network
Requires-Python: >=3.8,<4.0
Classifier: License :: OSI Approved :: MIT License
Classifier: Programming Language :: Python :: 3
Classifier: Programming Language :: Python :: 3.8
Classifier: Programming Language :: Python :: 3.9
Classifier: Programming Language :: Python :: 3.10
Classifier: Programming Language :: Python :: 3.11
Classifier: Programming Language :: Python :: 3.12
Requires-Dist: alchemy-sdk (>=0.1.1,<0.2.0)
Requires-Dist: dataclass_wizard (>=0.22.2,<0.23.0)
Requires-Dist: hexbytes (>=0.3.1,<0.4.0)
Requires-Dist: joblib (>=1.2.0,<2.0.0)
Requires-Dist: matplotlib (>=3.7.1,<4.0.0)
Requires-Dist: nest-asyncio (>=1.5.8,<2.0.0)
Requires-Dist: networkx (>=3.0,<4.0)
Requires-Dist: numpy (>=1.24.4,<2.0.0)
Requires-Dist: packaging (==21.3)
Requires-Dist: pandas (>=1.5.2,<2.0.0)
Requires-Dist: protobuf (>=4.24.4,<5.0.0)
Requires-Dist: psutil (>=5.9.6,<6.0.0)
Requires-Dist: pyarrow (>=11.0.0,<12.0.0)
Requires-Dist: python-dateutil (>=2.8.2,<3.0.0)
Requires-Dist: python-dotenv (>=0.16.0,<0.17.0)
Requires-Dist: requests (>=2.31.0,<3.0.0)
Requires-Dist: setuptools (>=67.6.1,<68.0.0)
Requires-Dist: tqdm (>=4.64.1,<5.0.0)
Requires-Dist: typing-extensions (>=4.7.1,<5.0.0)
Requires-Dist: web3 (>=6.16.0,<7.0.0)
